netHighTech_STT/__init__.py
netHighTech_STT/index.html
netHighTech_STT/input.txt
netHighTech_STT/script.js
netHighTech_STT/style.css
nethightech_stt-1.0.8.dist-info/METADATA
nethightech_stt-1.0.8.dist-info/WHEEL
nethightech_stt-1.0.8.dist-info/top_level.txt
nethightech_stt-1.0.8.dist-info/RECORD
