Metadata-Version: 2.4
Name: netHighTech_STT
Version: 1.0.8
Summary: Speech recognition Jarvis package
Author: Zubair Khan
Author-email: zubairdev00@gmail.com
Requires-Dist: selenium
Requires-Dist: webdriver-manager
Dynamic: author
Dynamic: author-email
Dynamic: requires-dist
Dynamic: summary
